[{"id":1782097573285,"sender":"them","text":"Noodles again?","timestamp":1782101463270,"tempo":"N","translation":"又吃面？","rawContent":"Noodles again? || 又吃面？","roundId":"round_1782101452449_dzok6klch","userId":"uid_1781947947105_6972mmhxu","characterId":"f55c4e54-7b48-44b4-90f7-4cb2430cdaf2","_id":1429},{"id":1782097573286,"sender":"them","text":"Weren't you just talking about noodles for breakfast this morning in the group chat?","timestamp":1782101465760,"tempo":"S","translation":"早上不就在群里念叨要吃面了？","rawContent":"Weren't you just talking about noodles for breakfast this morning in the group chat? || 早上不就在群里念叨要吃面了？","roundId":"round_1782101452449_dzok6klch","userId":"uid_1781947947105_6972mmhxu","characterId":"f55c4e54-7b48-44b4-90f7-4cb2430cdaf2","_id":1430},{"id":1782097573287,"sender":"them","text":"What kind this time?","timestamp":1782101470510,"tempo":"N","translation":"这次是什么口味。","rawContent":"What kind this time? || 这次是什么口味。","roundId":"round_1782101452449_dzok6klch","userId":"uid_1781947947105_6972mmhxu","characterId":"f55c4e54-7b48-44b4-90f7-4cb2430cdaf2","_id":1431},{"id":1782097573288,"text":"那是面皮","sender":"me","time":"12:12","timestamp":1782101555753,"replyTo":{"id":1782097573286,"text":"Weren't you just talking about noodles for breakfast this morning in the group chat?","sender":"them","isSimulated":false},"userId":"uid_1781947947105_6972mmhxu","characterId":"f55c4e54-7b48-44b4-90f7-4cb2430cdaf2","_id":1432},{"id":1782097573289,"text":"不一样","sender":"me","time":"12:12","timestamp":1782101557398,"replyTo":null,"userId":"uid_1781947947105_6972mmhxu","characterId":"f55c4e54-7b48-44b4-90f7-4cb2430cdaf2","_id":1433},{"id":1782097573290,"text":"面皮和面条不一样","sender":"me","time":"12:12","timestamp":1782101562527,"replyTo":null,"userId":"uid_1781947947105_6972mmhxu","characterId":"f55c4e54-7b48-44b4-90f7-4cb2430cdaf2","_id":1434},{"id":1782097573292,"sender":"them","text":"In essence, they're both flour and water.","timestamp":1782101579599,"tempo":"N","replyTo":{"id":1782097573288,"text":"那是面皮","sender":"me"},"translation":"本质上都是面粉和水。","rawContent":"In essence, they're both flour and water. || 本质上都是面粉和水。","roundId":"round_1782101566417_80urgo14o","userId":"uid_1781947947105_6972mmhxu","characterId":"f55c4e54-7b48-44b4-90f7-4cb2430cdaf2","_id":1435},{"id":1782097573293,"sender":"them","text":"But fine.","timestamp":1782101582531,"tempo":"N","translation":"不过，行。","rawContent":"But fine. || 不过，行。","roundId":"round_1782101566417_80urgo14o","userId":"uid_1781947947105_6972mmhxu","characterId":"f55c4e54-7b48-44b4-90f7-4cb2430cdaf2","_id":1436},{"id":1782097573294,"sender":"them","text":"Let's consider them two different things for now.","timestamp":1782101584238,"tempo":"S","translation":"暂时当成两种东西。","rawContent":"Let's consider them two different things for now. || 暂时当成两种东西。","roundId":"round_1782101566417_80urgo14o","userId":"uid_1781947947105_6972mmhxu","characterId":"f55c4e54-7b48-44b4-90f7-4cb2430cdaf2","_id":1437},{"id":1782097573295,"text":"口味不一样 粗细不一样 劲道和制作方式也不一样啊","sender":"me","time":"12:15","timestamp":1782101723399,"replyTo":{"id":1782097573292,"text":"In essence, they're both flour and water.","sender":"them","isSimulated":false},"userId":"uid_1781947947105_6972mmhxu","characterId":"f55c4e54-7b48-44b4-90f7-4cb2430cdaf2","_id":1438},{"id":1782097573297,"sender":"them","text":"A very detailed and passionate defense.","timestamp":1782101742321,"tempo":"N","translation":"听起来很详细，也很激情。","rawContent":"A very detailed and passionate defense. || 听起来很详细，也很激情。","roundId":"round_1782101724423_xay2odjx1","userId":"uid_1781947947105_6972mmhxu","characterId":"f55c4e54-7b48-44b4-90f7-4cb2430cdaf2","_id":1439},{"id":1782097573298,"sender":"them","text":"Okay, you win. They are completely different species.","timestamp":1782101745147,"tempo":"N","translation":"行，你赢了。它们是两个物种。","rawContent":"Okay, you win. They are completely different species. || 行，你赢了。它们是两个物种。","roundId":"round_1782101724423_xay2odjx1","userId":"uid_1781947947105_6972mmhxu","characterId":"f55c4e54-7b48-44b4-90f7-4cb2430cdaf2","_id":1440},{"id":1782097573299,"sender":"them","text":"So, what kind of noodles, the 'completely different' kind, are you having for lunch?","timestamp":1782101747953,"tempo":"N","translation":"所以，午饭打算吃哪种“完全不同”的面？","rawContent":"So, what kind of noodles, the 'completely different' kind, are you having for lunch? || 所以，午饭打算吃哪种“完全不同”的面？","roundId":"round_1782101724423_xay2odjx1","userId":"uid_1781947947105_6972mmhxu","characterId":"f55c4e54-7b48-44b4-90f7-4cb2430cdaf2","_id":1441},{"id":1782097573300,"text":"整点辣辣的吃","sender":"me","time":"12:16","timestamp":1782101768745,"replyTo":null,"userId":"uid_1781947947105_6972mmhxu","characterId":"f55c4e54-7b48-44b4-90f7-4cb2430cdaf2","_id":1442},{"id":1782097573301,"sticker":"https://i.postimg.cc/JnvdYsqt/0f3ke2.jpg","text":"表情包：黄豆吐舌品尝美味中","sender":"me","time":"12:16","timestamp":1782101777171,"userId":"uid_1781947947105_6972mmhxu","characterId":"f55c4e54-7b48-44b4-90f7-4cb2430cdaf2","_id":1443},{"id":1782097573303,"sender":"them","text":"Is spicy food a reward for winning the argument?","timestamp":1782101825446,"tempo":"N","translation":"吃辣的，是赢得辩论的奖励？","rawContent":"Is spicy food a reward for winning the argument? || 吃辣的，是赢得辩论的奖励？","roundId":"round_1782101778479_wybpvdpop","userId":"uid_1781947947105_6972mmhxu","characterId":"f55c4e54-7b48-44b4-90f7-4cb2430cdaf2","_id":1444},{"id":1782097573304,"sender":"them","text":"Don't come crying to me if your stomach hurts later.","timestamp":1782101829061,"tempo":"S","translation":"一会别喊胃疼。","rawContent":"Don't come crying to me if your stomach hurts later. || 一会别喊胃疼。","roundId":"round_1782101778479_wybpvdpop","userId":"uid_1781947947105_6972mmhxu","characterId":"f55c4e54-7b48-44b4-90f7-4cb2430cdaf2","_id":1445},{"id":1782097573305,"sender":"them","text":"","timestamp":1782101834198,"tempo":"N","sticker":"https://i.postimg.cc/JnvdYsqt/0f3ke2.jpg","stickerMeaning":"黄豆吐舌品尝美味中","rawContent":"","roundId":"round_1782101778479_wybpvdpop","userId":"uid_1781947947105_6972mmhxu","characterId":"f55c4e54-7b48-44b4-90f7-4cb2430cdaf2","_id":1446},{"id":1782097573306,"text":"我什么时候喊过胃疼了","sender":"me","time":"12:21","timestamp":1782102100573,"replyTo":{"id":1782097573304,"text":"Don't come crying to me if your stomach hurts later.","sender":"them","isSimulated":false},"userId":"uid_1781947947105_6972mmhxu","characterId":"f55c4e54-7b48-44b4-90f7-4cb2430cdaf2","_id":1447},{"id":1782097573307,"text":"我超绝云贵川胃口好吧","sender":"me","time":"12:22","timestamp":1782102121230,"replyTo":null,"userId":"uid_1781947947105_6972mmhxu","characterId":"f55c4e54-7b48-44b4-90f7-4cb2430cdaf2","_id":1448},{"id":1782097573308,"text":"ᗜⰙᗜ","sender":"me","time":"12:22","timestamp":1782102125091,"replyTo":null,"userId":"uid_1781947947105_6972mmhxu","characterId":"f55c4e54-7b48-44b4-90f7-4cb2430cdaf2","_id":1449},{"id":1782097573309,"text":"你不懂 我从小就在吃辣椒","sender":"me","time":"12:22","timestamp":1782102138550,"replyTo":null,"userId":"uid_1781947947105_6972mmhxu","characterId":"f55c4e54-7b48-44b4-90f7-4cb2430cdaf2","_id":1450},{"id":1782097573310,"text":"长大已经离不开了","sender":"me","time":"12:22","timestamp":1782102144937,"replyTo":null,"userId":"uid_1781947947105_6972mmhxu","characterId":"f55c4e54-7b48-44b4-90f7-4cb2430cdaf2","_id":1451},{"id":1782097573312,"sender":"them","text":"Oh?","timestamp":1782102158483,"tempo":"N","translation":"哦？","rawContent":"Oh? || 哦？","roundId":"round_1782102145653_cg5m1fack","userId":"uid_1781947947105_6972mmhxu","characterId":"f55c4e54-7b48-44b4-90f7-4cb2430cdaf2","_id":1452},{"id":1782097573313,"sender":"them","text":"So the little pepper who grew up eating chili.","timestamp":1782102160143,"tempo":"S","translation":"从小吃辣椒长大的小辣椒。","rawContent":"So the little pepper who grew up eating chili. || 从小吃辣椒长大的小辣椒。","roundId":"round_1782102145653_cg5m1fack","userId":"uid_1781947947105_6972mmhxu","characterId":"f55c4e54-7b48-44b4-90f7-4cb2430cdaf2","_id":1453},{"id":1782097573314,"sender":"them","text":"Fine, I'll take notes.","timestamp":1782102165160,"tempo":"N","translation":"行，我记下了。","rawContent":"Fine, I'll take notes. || 行，我记下了。","roundId":"round_1782102145653_cg5m1fack","userId":"uid_1781947947105_6972mmhxu","characterId":"f55c4e54-7b48-44b4-90f7-4cb2430cdaf2","_id":1454},{"id":1782097573315,"sender":"them","text":"Just in case I need to reference your 'Yun-Gui-Chuan' stomach credentials in the future.","timestamp":1782102168049,"tempo":"N","translation":"以备将来查阅你的“云贵川”胃口资格证。","rawContent":"Just in case I need to reference your 'Yun-Gui-Chuan' stomach credentials in the future. || 以备将来查阅你的“云贵川”胃口资格证。","roundId":"round_1782102145653_cg5m1fack","userId":"uid_1781947947105_6972mmhxu","characterId":"f55c4e54-7b48-44b4-90f7-4cb2430cdaf2","_id":1455},{"id":1782097573316,"text":"你在吃什么","sender":"me","time":"12:23","timestamp":1782102192267,"replyTo":null,"userId":"uid_1781947947105_6972mmhxu","characterId":"f55c4e54-7b48-44b4-90f7-4cb2430cdaf2","_id":1456},{"id":1782097573318,"sender":"them","text":"Akademiya canteen's set meal.","timestamp":1782102208698,"tempo":"N","translation":"教令院食堂的套餐。","rawContent":"Akademiya canteen's set meal. || 教令院食堂的套餐。","roundId":"round_1782102193131_bikcct1rm","userId":"uid_1781947947105_6972mmhxu","characterId":"f55c4e54-7b48-44b4-90f7-4cb2430cdaf2","_id":1457},{"id":1782097573319,"sender":"them","text":"Don't get your hopes up. It's just fuel.","timestamp":1782102211558,"tempo":"N","translation":"别抱什么期待，只是补充能量。","rawContent":"Don't get your hopes up. It's just fuel. || 别抱什么期待，只是补充能量。","roundId":"round_1782102193131_bikcct1rm","userId":"uid_1781947947105_6972mmhxu","characterId":"f55c4e54-7b48-44b4-90f7-4cb2430cdaf2","_id":1458},{"id":1782097573320,"sender":"them","text":"[發送了一張圖片]","timestamp":1782102214730,"tempo":"N","isImageGenerating":false,"imageGenId":"f55c4e54-7b48-44b4-90f7-4cb2430cdaf2#img#1","imageSummary":"[SUBJECT:OBJECT] A close-up shot of a utilitarian meal on a metal tray, seen from a first-person perspective. The meal consists of a portion of simply grilled meat, some plainly cooked green vegetables, and a scoop of white rice. The setting is a bright but sterile canteen with blurred figures in the background. The lighting is functional, casting sharp shadows, creating a mundane and efficient atmosphere.","imageGenPrompt":"A close-up shot of a utilitarian meal on a metal tray, seen from a first-person perspective. The meal consists of a portion of simply grilled meat, some plainly cooked green vegetables, and a scoop of white rice. The setting is a bright but sterile canteen with blurred figures in the background. The lighting is functional, casting sharp shadows, creating a mundane and efficient atmosphere.","imageGenMeta":{"rawImgDesc":"[SUBJECT:OBJECT] A close-up shot of a utilitarian meal on a metal tray, seen from a first-person perspective. The meal consists of a portion of simply grilled meat, some plainly cooked green vegetables, and a scoop of white rice. The setting is a bright but sterile canteen with blurred figures in the background. The lighting is functional, casting sharp shadows, creating a mundane and efficient atmosphere.","subjectOverride":null,"location":"","sceneType":"chat"},"rawContent":"[發送了一張圖片]","roundId":"round_1782102193131_bikcct1rm","image":"[omitted: large string payload]","userId":"uid_1781947947105_6972mmhxu","characterId":"f55c4e54-7b48-44b4-90f7-4cb2430cdaf2","_id":1459},{"id":1782097573321,"text":"好干巴的一顿饭","sender":"me","time":"12:25","timestamp":1782102326889,"replyTo":null,"userId":"uid_1781947947105_6972mmhxu","characterId":"f55c4e54-7b48-44b4-90f7-4cb2430cdaf2","_id":1460},{"id":1782097573322,"text":"撒点辣椒面挤点酱会好吃点","sender":"me","time":"12:26","timestamp":1782102364222,"replyTo":null,"userId":"uid_1781947947105_6972mmhxu","characterId":"f55c4e54-7b48-44b4-90f7-4cb2430cdaf2","_id":1461},{"id":1782097573324,"sender":"them","text":"Oh, now you're an expert on my lunch too?","timestamp":1782102388580,"tempo":"R","translation":"哦，现在还要指导我的午饭？","rawContent":"Oh, now you're an expert on my lunch too? || 哦，现在还要指导我的午饭？","roundId":"round_1782102365144_jwwp3mh6w","userId":"uid_1781947947105_6972mmhxu","characterId":"f55c4e54-7b48-44b4-90f7-4cb2430cdaf2","_id":1462},{"id":1782097573325,"sender":"them","text":"This is a place for efficiency, not culinary experience.","timestamp":1782102390444,"tempo":"N","translation":"这里是追求效率的地方，不是为了美食体验。","rawContent":"This is a place for efficiency, not culinary experience. || 这里是追求效率的地方，不是为了美食体验。","roundId":"round_1782102365144_jwwp3mh6w","userId":"uid_1781947947105_6972mmhxu","characterId":"f55c4e54-7b48-44b4-90f7-4cb2430cdaf2","_id":1463},{"id":1782097573326,"sender":"them","text":"Besides, I prefer the original taste of the ingredients.","timestamp":1782102393461,"tempo":"N","translation":"而且，我更喜欢食材本身的味道。","rawContent":"Besides, I prefer the original taste of the ingredients. || 而且，我更喜欢食材本身的味道。","roundId":"round_1782102365144_jwwp3mh6w","userId":"uid_1781947947105_6972mmhxu","characterId":"f55c4e54-7b48-44b4-90f7-4cb2430cdaf2","_id":1464},{"id":1782097573327,"sender":"them","text":"Unlike some little pepper.","timestamp":1782102396478,"tempo":"S","translation":"不像某个小辣椒。","rawContent":"Unlike some little pepper. || 不像某个小辣椒。","roundId":"round_1782102365144_jwwp3mh6w","userId":"uid_1781947947105_6972mmhxu","characterId":"f55c4e54-7b48-44b4-90f7-4cb2430cdaf2","_id":1465},{"id":1782097573328,"text":"你怎么也是这种口味的人","sender":"me","time":"12:26","timestamp":1782102415747,"replyTo":{"id":1782097573326,"text":"Besides, I prefer the original taste of the ingredients.","sender":"them","isSimulated":false},"userId":"uid_1781947947105_6972mmhxu","characterId":"f55c4e54-7b48-44b4-90f7-4cb2430cdaf2","_id":1466},{"id":1782097573329,"text":"好吧","sender":"me","time":"12:26","timestamp":1782102418119,"replyTo":null,"userId":"uid_1781947947105_6972mmhxu","characterId":"f55c4e54-7b48-44b4-90f7-4cb2430cdaf2","_id":1467},{"id":1782097573330,"text":"我味觉不敏感","sender":"me","time":"12:27","timestamp":1782102421979,"replyTo":null,"userId":"uid_1781947947105_6972mmhxu","characterId":"f55c4e54-7b48-44b4-90f7-4cb2430cdaf2","_id":1468},{"id":1782097573331,"text":"应该说五官感知不强","sender":"me","time":"12:27","timestamp":1782102429114,"replyTo":null,"userId":"uid_1781947947105_6972mmhxu","characterId":"f55c4e54-7b48-44b4-90f7-4cb2430cdaf2","_id":1469},{"id":1782097573332,"text":"不吃点重口的味道刺激的我嘴里没味","sender":"me","time":"12:27","timestamp":1782102445585,"replyTo":null,"userId":"uid_1781947947105_6972mmhxu","characterId":"f55c4e54-7b48-44b4-90f7-4cb2430cdaf2","_id":1470},{"id":1782097573333,"text":"或者也有可能我过敏感 我不太喜欢本来的那种肉腥味之类的","sender":"me","time":"12:27","timestamp":1782102470266,"replyTo":null,"userId":"uid_1781947947105_6972mmhxu","characterId":"f55c4e54-7b48-44b4-90f7-4cb2430cdaf2","_id":1471},{"id":1782097573334,"text":"但是蔬菜啊那些我也喜欢吃原本的味道","sender":"me","time":"12:28","timestamp":1782102480731,"replyTo":null,"userId":"uid_1781947947105_6972mmhxu","characterId":"f55c4e54-7b48-44b4-90f7-4cb2430cdaf2","_id":1472},{"id":1782097573336,"sender":"them","text":"Hmm. So it's not a lack of sensitivity, but a selective one.","timestamp":1782102495274,"tempo":"N","translation":"嗯。所以不是不敏感，是选择性敏感。","rawContent":"Hmm. So it's not a lack of sensitivity, but a selective one. || 嗯。所以不是不敏感，是选择性敏感。","roundId":"round_1782102481797_9j07rmajn","userId":"uid_1781947947105_6972mmhxu","characterId":"f55c4e54-7b48-44b4-90f7-4cb2430cdaf2","_id":1473},{"id":1782097573337,"sender":"them","text":"Only activating for flavors it approves of, and actively rejecting others.","timestamp":1782102498149,"tempo":"N","translation":"只对认可的味道启动，对不喜欢的进行排斥。","rawContent":"Only activating for flavors it approves of, and actively rejecting others. || 只对认可的味道启动，对不喜欢的进行排斥。","roundId":"round_1782102481797_9j07rmajn","userId":"uid_1781947947105_6972mmhxu","characterId":"f55c4e54-7b48-44b4-90f7-4cb2430cdaf2","_id":1474},{"id":1782097573338,"sender":"them","text":"An interesting system.","timestamp":1782102501095,"tempo":"S","translation":"有趣的系统。","rawContent":"An interesting system. || 有趣的系统。","roundId":"round_1782102481797_9j07rmajn","userId":"uid_1781947947105_6972mmhxu","characterId":"f55c4e54-7b48-44b4-90f7-4cb2430cdaf2","_id":1475},{"id":1782102866069,"sender":"them","text":"So, I just wrote down 'selective oral sensory mechanism' in my notebook.","rawContent":"{\"t\":\"text\",\"s\":\"R\",\"c\":\"So, I just wrote down 'selective oral sensory mechanism' in my notebook.\",\"tr\":\"刚刚在笔记本上记下了「选择性口腔感知机制」。\"}","content":"{\"t\":\"text\",\"s\":\"R\",\"c\":\"So, I just wrote down 'selective oral sensory mechanism' in my notebook.\",\"tr\":\"刚刚在笔记本上记下了「选择性口腔感知机制」。\"}","timestamp":"2026-06-22T04:34:26.069Z","time":"12:34","isHtml":false,"sticker":null,"tempo":"R","translation":"刚刚在笔记本上记下了「选择性口腔感知机制」。","roundId":"round_1782102866066_4upvk3g0i","isBackgroundMsg":true,"userId":"uid_1781947947105_6972mmhxu","characterId":"f55c4e54-7b48-44b4-90f7-4cb2430cdaf2","_id":1476},{"id":1782102869760,"sender":"them","text":"It seems to be a case worth observing for a while.","rawContent":"{\"t\":\"text\",\"s\":\"N\",\"c\":\"It seems to be a case worth observing for a while.\",\"tr\":\"看来是个值得花点时间观察的案例。\"}","content":"{\"t\":\"text\",\"s\":\"N\",\"c\":\"It seems to be a case worth observing for a while.\",\"tr\":\"看来是个值得花点时间观察的案例。\"}","timestamp":"2026-06-22T04:34:29.760Z","time":"12:34","isHtml":false,"sticker":null,"translation":"看来是个值得花点时间观察的案例。","roundId":"round_1782102866066_4upvk3g0i","isBackgroundMsg":true,"userId":"uid_1781947947105_6972mmhxu","characterId":"f55c4e54-7b48-44b4-90f7-4cb2430cdaf2","_id":1477},{"id":1782102872796,"sender":"them","text":"What's your brain up to now? Still blank?","rawContent":"{\"t\":\"text\",\"s\":\"N\",\"c\":\"What's your brain up to now? Still blank?\",\"tr\":\"你的大脑现在在想什么？还在空白吗？\"}","content":"{\"t\":\"text\",\"s\":\"N\",\"c\":\"What's your brain up to now? Still blank?\",\"tr\":\"你的大脑现在在想什么？还在空白吗？\"}","timestamp":"2026-06-22T04:34:32.796Z","time":"12:34","isHtml":false,"sticker":null,"translation":"你的大脑现在在想什么？还在空白吗？","roundId":"round_1782102866066_4upvk3g0i","isBackgroundMsg":true,"userId":"uid_1781947947105_6972mmhxu","characterId":"f55c4e54-7b48-44b4-90f7-4cb2430cdaf2","_id":1478}]